python_project_starter/__init__.py
python_project_starter/__main__.py
python_project_starter/template/.gitignore
python_project_starter/template/README.md
python_project_starter/template/setup.py
python_project_starter/template/my_project/__init__.py
python_project_starter/template/my_project/__main__.py
python_project_starter-1.3.dist-info/LICENSE
python_project_starter-1.3.dist-info/METADATA
python_project_starter-1.3.dist-info/WHEEL
python_project_starter-1.3.dist-info/entry_points.txt
python_project_starter-1.3.dist-info/top_level.txt
python_project_starter-1.3.dist-info/RECORD
