Metadata-Version: 2.1
Name: python-project-starter
Version: 1.3
Summary: This package permit you to easily create a new project
Home-page: https://github.com/henri9813/python-project-starter
Author: Henri Devigne
Author-email: henri.devigne@bonkgaming.fr
License: UNKNOWN
Platform: UNKNOWN
